{"dr-search_hci_9000000008":{"hcpId":"9265486345","hciId":"9000000008","nameEng":"Quality Healthcare Medical Centre","nameChiT":"卓健醫療中心","officialNameEng":"Quality Healthcare Medical Centre","officialNameChiT":"卓健醫療中心","shortNameEng":"QUALITY HEALTHCARE","shortNameChiT":"卓健醫療中心","providerTypeCd":"I","typeOfHCPCd":"SOLO","typeOfHCPShortDesc":"Solo Practice","phoneNo":null,"email":null,"website":null,"districtEng":"KWUN TONG DISTRICT","districtChiT":"觀塘區","addressEng":"G/F,BLOCK 1,TELFORD GARDEN,KWUN TONG DISTRICT,KOWLOON","addressChiT":"九龍觀塘區德福花園一座地下","newbornrcInd":"0","ehrcInd":"0","monOH":"(08:00-18:00)","tueOH":"(08:00-18:00)","wedOH":"(08:00-18:00)","thurOH":"(08:00-18:00)","friOH":"(08:00-18:00)","satOH":"(08:00-13:00)","sunOH":"No Service","pubOH":"No Service","remarkPubOH":"No Service","remarkPubOHChi":"無服務","adr":"1","al1":"1","birth":"1","enctr":"1","epis":"1","immu":"1","invr":"1","labap":"1","labgen":"1","labmb":"1","pmi":"1","prob":"1","px":"1","rad":"1","ref":"1","rxd":"1","rxo":"1","obs":"1","endo":"1","lastUpdDtm":"1565775995427","typeOfHCPLongDesc":"Solo Practice","hcpInfo":{"hcpId":"9265486345","nameEng":"QUALITY HEALTHCARE MEDICAL CENTRE LIMITED","nameChiT":"卓健醫療體檢中心有限公司","hcpLink":{"href":"/dr-search/hcp/9265486345","rel":"getHcpDetail"},"progResult":null}}}